curly_comparer/__init__.py
curly_comparer/algorithms/levenshtein.py
curly_comparer-0.1.1.dist-info/LICENSE
curly_comparer-0.1.1.dist-info/METADATA
curly_comparer-0.1.1.dist-info/WHEEL
curly_comparer-0.1.1.dist-info/top_level.txt
curly_comparer-0.1.1.dist-info/RECORD
