Metadata-Version: 2.1
Name: curly_comparer
Version: 0.1.1
Summary: A little package with string comparison tools
Author-email: Pedro Lopez Guzman <pdihax@gmail.com>
License: Apache License 2.0
Project-URL: Homepage, https://github.com/Pedro-UwU/curly-comparer
Requires-Python: >=3.10
License-File: LICENSE
Requires-Dist: numpy>=2.1
Provides-Extra: dev
Requires-Dist: pytest; extra == "dev"
Requires-Dist: numpy; extra == "dev"
